{
  "!type": "OffCanvas_bs5",
  "backgroundColor": "",
  "badge": "",
  "badgeAppearance": " bg-info",
  "borderColor": "",
  "borderStyle": "",
  "borderWidth": "",
  "bottom": "auto",
  "cached_js": "",
  "cached_js_script_hash": "d41d8cd98f00b204e9800998ecf8427e",
  "children": [],
  "class": "",
  "color": "",
  "display": "",
  "expanded_pmp": null,
  "fontFamily": "",
  "fontSize": "",
  "fontStyle": "",
  "fontWeight": "",
  "footer": "Footer",
  "header": "OffCanvas",
  "height": "auto",
  "hidden": "display:none; ",
  "id": "OffCanvas1",
  "left": 90,
  "mAll": "",
  "mBottom": "",
  "mLeft": "",
  "mRight": "",
  "mTop": "",
  "onclick": "",
  "onmousedown": "",
  "onmousemove": "",
  "onmouseout": "",
  "onmouseup": "",
  "onresize": "",
  "ontouchend": "",
  "ontouchmove": "",
  "ontouchstart": "",
  "pAll": "",
  "pBottom": "",
  "pLeft": "",
  "pRight": "",
  "pTop": "",
  "position": " offcanvas-start",
  "right": "auto",
  "script": "",
  "size": "offcanvas",
  "style": "",
  "top": 210,
  "value": "Content for the offcanvas goes here. You can place just about any Bootstrap component or custom elements here.",
  "width": "auto"
}